[
    {
        "id": 1,
        "en": "Unit One",
        "lessons": [
            {
                "id": 1,
                "en": "Finding fossil man",
                "zh": "发现化石人"
            },
            {
                "id": 2,
                "en": "Spare that spider",
                "zh": "不要伤害蜘蛛"
            },
            {
                "id": 3,
                "en": "Matterhorn man",
                "zh": "马特霍恩山区人"
            },
            {
                "id": 4,
                "en": "Seeing hands",
                "zh": "能看见东西的手"
            },
            {
                "id": 5,
                "en": "Youth",
                "zh": "青年"
            },
            {
                "id": 6,
                "en": "The sporting spirit",
                "zh": "体育的精神"
            },
            {
                "id": 7,
                "en": "Bats",
                "zh": "蝙蝠"
            },
            {
                "id": 8,
                "en": "Trading standards",
                "zh": "贸易标准"
            }
        ]
    },
    {
        "id": 2,
        "en": "Unit Two",
        "lessons": [
            {
                "id": 9,
                "en": "Royal espionage",
                "zh": "王室谍报活动"
            },
            {
                "id": 10,
                "en": " Silicon valley",
                "zh": "硅谷"
            },
            {
                "id": 11,
                "en": " How to grow old",
                "zh": "如何安度晚年"
            },
            {
                "id": 12,
                "en": " Banks and their customers",
                "zh": "银行和顾客"
            },
            {
                "id": 13,
                "en": " The search for oil",
                "zh": "探寻石油"
            },
            {
                "id": 14,
                "en": " The Butterfly Effect",
                "zh": "蝴蝶效应"
            },
            {
                "id": 15,
                "en": " Secrecy in industry",
                "zh": "工业中的秘密"
            },
            {
                "id": 16,
                "en": " The modern city",
                "zh": "现代城市"
            }
        ]
    },
    {
        "id": 3,
        "en": "Unit Three",
        "lessons": [
            {
                "id": 17,
                "en": " A man-made disease",
                "zh": "人为的疾病"
            },
            {
                "id": 18,
                "en": " Porpoises",
                "zh": "海豚"
            },
            {
                "id": 19,
                "en": " The stuff of dreams",
                "zh": "话说梦的本质"
            },
            {
                "id": 20,
                "en": " Snake poison",
                "zh": "蛇毒"
            },
            {
                "id": 21,
                "en": " Williams S．Hart and the early‘Western’film威廉·S．",
                "zh": "哈特和早期的“西部”影片"
            },
            {
                "id": 22,
                "en": " Knowledge and progress",
                "zh": "知识和进步"
            },
            {
                "id": 23,
                "en": " Bird flight",
                "zh": "鸟的飞行方法"
            },
            {
                "id": 24,
                "en": " Beauty",
                "zh": "美"
            }
        ]
    },
    {
        "id": 4,
        "en": "Unit Four",
        "lessons": [
            {
                "id": 25,
                "en": " Non-auditory effects of noise",
                "zh": "噪音的非听觉效应"
            },
            {
                "id": 26,
                "en": " The past life of the earth",
                "zh": "地球上的昔日生命"
            },
            {
                "id": 27,
                "en": " The‘Vasa’",
                "zh": "“瓦萨”号"
            },
            {
                "id": 28,
                "en": " Patients and doctors",
                "zh": "病人与医生"
            },
            {
                "id": 29,
                "en": " The hovercraft",
                "zh": "气垫船"
            },
            {
                "id": 30,
                "en": " Exploring the sea．floor",
                "zh": "海底勘探"
            },
            {
                "id": 31,
                "en": " The sculptor speaks",
                "zh": "雕塑家的语言"
            },
            {
                "id": 32,
                "en": " Galileo reborn",
                "zh": "伽利略的复生"
            }
        ]
    },
    {
        "id": 5,
        "en": "Unit Five",
        "lessons": [
            {
                "id": 33,
                "en": " Education",
                "zh": "教育"
            },
            {
                "id": 34,
                "en": " Adolescence",
                "zh": "青春期"
            },
            {
                "id": 35,
                "en": " Space odyssey",
                "zh": "太空探索"
            },
            {
                "id": 36,
                "en": " The cost of government",
                "zh": "政府的开支"
            },
            {
                "id": 37,
                "en": " The process of ageing",
                "zh": "衰老过程"
            },
            {
                "id": 38,
                "en": " Water and the traveller",
                "zh": "水和旅行者"
            },
            {
                "id": 39,
                "en": " What every writer wants",
                "zh": "作家之所需"
            },
            {
                "id": 40,
                "en": " Waves",
                "zh": "海浪"
            }
        ]
    },
    {
        "id": 6,
        "en": "Unit Six",
        "lessons": [
            {
                "id": 41,
                "en": " Training elephants",
                "zh": "训练大象"
            },
            {
                "id": 42,
                "en": " Recording an earthquake",
                "zh": "记录地震"
            },
            {
                "id": 43,
                "en": " Are there strangers in space?",
                "zh": "宇宙中有外星人吗?"
            },
            {
                "id": 44,
                "en": " Patterns of culture",
                "zh": "文化的模式"
            },
            {
                "id": 45,
                "en": " Of men and galaxies",
                "zh": "人和星系"
            },
            {
                "id": 46,
                "en": " Hobbies",
                "zh": "业余爱好"
            },
            {
                "id": 47,
                "en": " The great escape",
                "zh": "大逃亡"
            },
            {
                "id": 48,
                "en": " Planning a share portfolio",
                "zh": "规划股份投资"
            }
        ]
    }
]